{"site_name": "www.nordlys.no", "description": "Dette bildet dukket forleden opp p\u00e5 snapchat-kontoen party.tromso, hvor innsenderen har tatt bilde i det vedkommende tilsynelatende ruller seg en hasjsigarett. Nordlys har vist Anita\u2026", "title": "- Jeg skulle \u00f8nske at flere tok avstand fra dette", "url": "http://www.nordlys.no/hasj/narkotika/sosiale-medier/jeg-skulle-onske-at-flere-tok-avstand-fra-dette/s/5-34-237040", "image": "http://g.api.no/obscura/API/dynamic/r1/ece5/tr_1080_733_l_f/0000/noly/2015/9/3/16/anita.jpg?chk=467A5E", "date": "2015-09-03 19:56:00", "type": "story"}